__init__.py
bemi.py
bemi_sqlalchemy-0.0.2.dist-info/licenses/LICENSE
bemi_sqlalchemy-0.0.2.dist-info/METADATA
bemi_sqlalchemy-0.0.2.dist-info/WHEEL
bemi_sqlalchemy-0.0.2.dist-info/top_level.txt
bemi_sqlalchemy-0.0.2.dist-info/RECORD
