Metadata-Version: 2.4
Name: bemi-sqlalchemy
Version: 0.0.2
Summary: Automatic data change tracking for SQLAlchemy
Author-email: Evgeny Li <evgeny@bemi.io>
License:                    GNU LESSER GENERAL PUBLIC LICENSE
Project-URL: Homepage, https://github.com/BemiHQ/bemi-sqlalchemy
Project-URL: Issues, https://github.com/BemiHQ/bemi-sqlalchemy/issues
Project-URL: Documentation, https://docs.bemi.io/orms/sqlalchemy
Classifier: Intended Audience :: Information Technology
Classifier: Intended Audience :: System Administrators
Classifier: Intended Audience :: Developers
Classifier: Operating System :: OS Independent
Classifier: Topic :: Software Development :: Libraries :: Application Frameworks
Classifier: Topic :: Software Development :: Libraries :: Python Modules
Classifier: Topic :: Software Development :: Libraries
Classifier: Topic :: Software Development
Classifier: Topic :: Database
Classifier: Programming Language :: Python
Classifier: Programming Language :: Python :: 3
Classifier: Programming Language :: Python :: 3 :: Only
Classifier: Programming Language :: Python :: 3.8
Classifier: Programming Language :: Python :: 3.9
Classifier: Programming Language :: Python :: 3.10
Classifier: Programming Language :: Python :: 3.11
Classifier: Programming Language :: Python :: 3.12
Classifier: License :: OSI Approved :: GNU Lesser General Public License v3 (LGPLv3)
Requires-Python: >=3.8
License-File: LICENSE
Requires-Dist: alembic
Requires-Dist: sqlalchemy
Requires-Dist: typing-extensions>=4.8.0
Dynamic: license-file
